mri_nufft-1.3.1.dist-info/licenses/LICENSE.txt
mrinufft/__init__.py
mrinufft/_array_compat.py
mrinufft/_utils.py
mrinufft/_version.py
mrinufft/density/__init__.py
mrinufft/density/geometry_based.py
mrinufft/density/nufft_based.py
mrinufft/density/utils.py
mrinufft/extras/__init__.py
mrinufft/extras/cartesian.py
mrinufft/extras/data.py
mrinufft/extras/field_map.py
mrinufft/extras/optim.py
mrinufft/extras/smaps.py
mrinufft/io/__init__.py
mrinufft/io/cfl.py
mrinufft/io/nsp.py
mrinufft/io/siemens.py
mrinufft/io/utils.py
mrinufft/operators/__init__.py
mrinufft/operators/autodiff.py
mrinufft/operators/base.py
mrinufft/operators/off_resonance.py
mrinufft/operators/stacked.py
mrinufft/operators/subspace.py
mrinufft/operators/interfaces/__init__.py
mrinufft/operators/interfaces/bart.py
mrinufft/operators/interfaces/cufinufft.py
mrinufft/operators/interfaces/finufft.py
mrinufft/operators/interfaces/gpunufft.py
mrinufft/operators/interfaces/nfft.py
mrinufft/operators/interfaces/nudft_numpy.py
mrinufft/operators/interfaces/pynufft_cpu.py
mrinufft/operators/interfaces/sigpy.py
mrinufft/operators/interfaces/tfnufft.py
mrinufft/operators/interfaces/torchkbnufft.py
mrinufft/operators/interfaces/utils/__init__.py
mrinufft/operators/interfaces/utils/css_color.txt
mrinufft/operators/interfaces/utils/gpu_utils.py
mrinufft/trajectories/__init__.py
mrinufft/trajectories/display.py
mrinufft/trajectories/display3D.py
mrinufft/trajectories/gradients.py
mrinufft/trajectories/projection.py
mrinufft/trajectories/sampling.py
mrinufft/trajectories/tools.py
mrinufft/trajectories/trajectory2D.py
mrinufft/trajectories/trajectory3D.py
mrinufft/trajectories/utils.py
mrinufft/trajectories/inits/__init__.py
mrinufft/trajectories/inits/eccentric.py
mrinufft/trajectories/inits/random_walk.py
mrinufft/trajectories/inits/travelling_salesman.py
mrinufft/trajectories/maths/__init__.py
mrinufft/trajectories/maths/fibonacci.py
mrinufft/trajectories/maths/primes.py
mrinufft/trajectories/maths/rotations.py
mrinufft/trajectories/maths/tsp_solver.py
mri_nufft-1.3.1.dist-info/METADATA
mri_nufft-1.3.1.dist-info/WHEEL
mri_nufft-1.3.1.dist-info/top_level.txt
mri_nufft-1.3.1.dist-info/RECORD
