Metadata-Version: 2.4
Name: mri-nufft
Version: 1.3.1
Summary: MRI Non-Cartesian Fourier Operators with multiple computation backends.
Author-email: Pierre-antoine Comby <pierre-antoine.comby@crans.org>
Requires-Python: >=3.10
License-File: LICENSE.txt
Requires-Dist: numpy>=2.2
Requires-Dist: scipy>=1.13
Requires-Dist: matplotlib>=3.9
Requires-Dist: tqdm
Requires-Dist: joblib>=1.4
Provides-Extra: gpunufft
Requires-Dist: gpuNUFFT>=0.10.1; extra == "gpunufft"
Requires-Dist: cupy-cuda12x; extra == "gpunufft"
Provides-Extra: torchkbnufft
Requires-Dist: torchkbnufft; extra == "torchkbnufft"
Requires-Dist: cupy-cuda12x; extra == "torchkbnufft"
Provides-Extra: torchkbnufft-cpu
Requires-Dist: torchkbnufft; extra == "torchkbnufft-cpu"
Requires-Dist: cupy-cuda12x; extra == "torchkbnufft-cpu"
Provides-Extra: torchkbnufft-gpu
Requires-Dist: torchkbnufft; extra == "torchkbnufft-gpu"
Requires-Dist: cupy-cuda12x; extra == "torchkbnufft-gpu"
Provides-Extra: cufinufft
Requires-Dist: cufinufft>=2.4.0; extra == "cufinufft"
Requires-Dist: cupy-cuda12x; extra == "cufinufft"
Provides-Extra: tensorflow
Requires-Dist: tensorflow-mri>=0.22.0; extra == "tensorflow"
Provides-Extra: finufft
Requires-Dist: finufft>=2.4.0; extra == "finufft"
Provides-Extra: sigpy
Requires-Dist: sigpy; extra == "sigpy"
Provides-Extra: pynfft
Requires-Dist: pynfft3; extra == "pynfft"
Provides-Extra: pynufft
Requires-Dist: pynufft; extra == "pynufft"
Provides-Extra: pynufft-cpu
Requires-Dist: pynufft; extra == "pynufft-cpu"
Provides-Extra: pynufft-gpu
Requires-Dist: pynufft; extra == "pynufft-gpu"
Provides-Extra: io
Requires-Dist: pymapvbvd; extra == "io"
Provides-Extra: extra
Requires-Dist: pymapvbvd; extra == "extra"
Requires-Dist: scikit-image; extra == "extra"
Requires-Dist: scikit-learn; extra == "extra"
Requires-Dist: pywavelets; extra == "extra"
Provides-Extra: autodiff
Requires-Dist: torch; extra == "autodiff"
Provides-Extra: test
Requires-Dist: pytest<8.0.0; extra == "test"
Requires-Dist: pytest-cov; extra == "test"
Requires-Dist: pytest-xdist; extra == "test"
Requires-Dist: pytest-sugar; extra == "test"
Requires-Dist: pytest-cases; extra == "test"
Provides-Extra: dev
Requires-Dist: black; extra == "dev"
Requires-Dist: isort; extra == "dev"
Requires-Dist: ruff; extra == "dev"
Provides-Extra: doc
Requires-Dist: sphinx-book-theme; extra == "doc"
Requires-Dist: sphinx-copybutton; extra == "doc"
Requires-Dist: sphinxcontrib-video; extra == "doc"
Requires-Dist: sphinx-gallery; extra == "doc"
Requires-Dist: matplotlib; extra == "doc"
Requires-Dist: pooch; extra == "doc"
Requires-Dist: brainweb-dl; extra == "doc"
Requires-Dist: coverage; extra == "doc"
Requires-Dist: fastmri; extra == "doc"
Dynamic: license-file
